clericus/__init__.py
clericus/authentication/__init__.py
clericus/config/__init__.py
clericus/db/__init__.py
clericus/db/transactions.py
clericus/errors/__init__.py
clericus/errors/mongo.py
clericus/handler/__init__.py
clericus/handler/documentation.py
clericus/middleware/__init__.py
clericus/parsing/__init__.py
clericus/parsing/errors.py
clericus/parsing/fields.py
clericus/routes/__init__.py
clericus/routes/authentication.py
clericus/routes/health.py
clericus/routes/permissions.py
clericus/schemas/__init__.py
clericus/schemas/activity.py
clericus/schemas/authentication.py
clericus/schemas/permissions.py
clericus/schemas/user.py
clericus/tests/__init__.py
clericus/tests/test_case.py
clericus/tests/test_login.py
clericus/tests/test_parsing.py
clericus/tests/test_signup.py
clericus-0.0.3.dist-info/LICENSE
clericus-0.0.3.dist-info/METADATA
clericus-0.0.3.dist-info/WHEEL
clericus-0.0.3.dist-info/top_level.txt
clericus-0.0.3.dist-info/RECORD
