Metadata-Version: 2.1
Name: clericus
Version: 0.0.3
Summary: An async webserver focused on being predictable and self documenting.
Home-page: https://github.com/mrincredibuell/clericus
Author: Joseph L Buell V
Author-email: jlrbuellv@gmail.com
License: UNKNOWN
Platform: UNKNOWN
Classifier: Programming Language :: Python :: 3
Classifier: License :: OSI Approved :: MIT License
Classifier: Operating System :: OS Independent
Classifier: Development Status :: 3 - Alpha
Requires-Dist: aiohttp (>=3.5.4)
Requires-Dist: pyjwt (>=1.7.1)
Requires-Dist: motor (>=2.0.0)
Requires-Dist: python-dateutil (>=2.8.0)
Requires-Dist: bcrypt (>=3.1.6)
Requires-Dist: dnspython (>=1.16.0)
